apitable/__init__.py
apitable/apitable.py
apitable/const.py
apitable/datasheet/__init__.py
apitable/datasheet/datasheet.py
apitable/datasheet/datasheet_manager.py
apitable/datasheet/field_manager.py
apitable/datasheet/query_set.py
apitable/datasheet/record.py
apitable/datasheet/record_manager.py
apitable/datasheet/view_manager.py
apitable/exceptions.py
apitable/node/__init__.py
apitable/node/node_manager.py
apitable/request.py
apitable/space/__init__.py
apitable/space/space.py
apitable/space/space_manager.py
apitable/types/__init__.py
apitable/types/embedlink.py
apitable/types/field.py
apitable/types/node.py
apitable/types/record.py
apitable/types/response.py
apitable/types/space.py
apitable/types/unit_model.py
apitable/types/view.py
apitable/unit/__init__.py
apitable/unit/member.py
apitable/unit/role.py
apitable/unit/team.py
apitable/unit/unit.py
apitable/utils.py
apitable-1.4.2.dist-info/LICENSE
apitable-1.4.2.dist-info/METADATA
apitable-1.4.2.dist-info/WHEEL
apitable-1.4.2.dist-info/RECORD
